ssllabs/__init__.py
ssllabs/ssllabs.py
ssllabs/api/__init__.py
ssllabs/api/_api.py
ssllabs/api/analyze.py
ssllabs/api/endpoint.py
ssllabs/api/info.py
ssllabs/api/root_certs_raw.py
ssllabs/api/status_codes.py
ssllabs/data/__init__.py
ssllabs/data/caa_policy.py
ssllabs/data/caa_record.py
ssllabs/data/cert.py
ssllabs/data/certificate_chain.py
ssllabs/data/drown_hosts.py
ssllabs/data/endpoint.py
ssllabs/data/endpoint_details.py
ssllabs/data/host.py
ssllabs/data/hpkp_policy.py
ssllabs/data/hsts_policy.py
ssllabs/data/hsts_preload.py
ssllabs/data/http_transaction.py
ssllabs/data/info.py
ssllabs/data/named_group.py
ssllabs/data/named_groups.py
ssllabs/data/protocol.py
ssllabs/data/protocol_suites.py
ssllabs/data/sim_client.py
ssllabs/data/sim_details.py
ssllabs/data/simulation.py
ssllabs/data/static_pkp_policy.py
ssllabs/data/status_codes.py
ssllabs/data/suite.py
ssllabs/data/trust.py
ssllabs/data/trust_path.py
ssllabs-1.2.2.dist-info/LICENSE.md
ssllabs-1.2.2.dist-info/METADATA
ssllabs-1.2.2.dist-info/WHEEL
ssllabs-1.2.2.dist-info/top_level.txt
ssllabs-1.2.2.dist-info/RECORD
