Metadata-Version: 2.1
Name: ssllabs
Version: 1.2.2
Summary: Qualys SSL Labs API in Python
Home-page: https://github.com/devolo/ssllabs
Author: Markus Bong, Guido Schmitz
Author-email: m.bong@famabo.de, guido.schmitz@fedaix.de
License: MIT
Classifier: Programming Language :: Python :: 3
Classifier: License :: OSI Approved :: MIT License
Classifier: Operating System :: OS Independent
Requires-Python: >=3.7
License-File: LICENSE.md
Requires-Dist: dacite
Requires-Dist: httpx
Requires-Dist: importlib-metadata ; python_version < "3.8"
Provides-Extra: dev
Requires-Dist: pre-commit ; extra == 'dev'
Provides-Extra: docs
Requires-Dist: m2r2 ; extra == 'docs'
Requires-Dist: pydata-sphinx-theme ; extra == 'docs'
Requires-Dist: sphinx ; extra == 'docs'
Provides-Extra: test
Requires-Dist: pytest ; extra == 'test'
Requires-Dist: pytest-asyncio ; extra == 'test'
Requires-Dist: pytest-cov ; extra == 'test'
Requires-Dist: pytest-httpx ; extra == 'test'
Requires-Dist: pytest-mock ; extra == 'test'
Requires-Dist: asynctest ; (python_version < "3.8") and extra == 'test'
